invoices/__init__.py
invoices/admin.py
invoices/apps.py
invoices/constants.py
invoices/helpers.py
invoices/models.py
invoices/views.py
invoices/migrations/0001_initial.py
invoices/migrations/__init__.py
invoices/services/__init__.py
invoices/services/invoice_service.py
invoices/services/xml_service.py
invoices/tests/__init__.py
invoices/tests/test_models.py
zatca/__init__.py
zatca/admin.py
zatca/apps.py
zatca/models.py
zatca/tests.py
zatca/views.py
zatca/integrations/__init__.py
zatca/integrations/zatca.py
zatca/migrations/0001_initial.py
zatca/migrations/__init__.py
zatca/services/__init__.py
zatca/services/onboarding.py
zatca/services/renewing.py
takamol_einvoicer_test_app-0.1.dist-info/LICENSE
takamol_einvoicer_test_app-0.1.dist-info/METADATA
takamol_einvoicer_test_app-0.1.dist-info/WHEEL
takamol_einvoicer_test_app-0.1.dist-info/top_level.txt
takamol_einvoicer_test_app-0.1.dist-info/RECORD
